[
  {
    "type": "text",
    "id": "author",
    "title": "Author",
    "placeholder": "Search for authors..."
  },
  {
    "type": "sort",
    "name": "Sort",
    "canAscend": true,
    "options": [
      "Relevance",
      "Popularity",
      "Average Rating",
      "Last Update",
      "Release Date",
      "Followers",
      "Number of Pages",
      "Views",
      "Title",
      "Author"
    ],
    "ids": [
      "relevance",
      "popularity",
      "rating",
      "last_update",
      "release_date",
      "followers",
      "length",
      "views",
      "title",
      "author"
    ],
    "default": {
      "index": 0,
      "ascending": false
    }
  },
  {
    "type": "multi-select",
    "id": "genre",
    "title": "Genres",
    "isGenre": true,
    "canExclude": true,
    "options": [
      "Action",
      "Adventure",
      "Comedy",
      "Contemporary",
      "Drama",
      "Fantasy",
      "Historical",
      "Horror",
      "Mystery",
      "Psychological",
      "Romance",
      "Satire",
      "Sci-Fi",
      "Short Story",
      "Thriller",
      "Tragedy"
    ],
    "ids": [
      "action",
      "adventure",
      "comedy",
      "contemporary",
      "drama",
      "fantasy",
      "historical",
      "horror",
      "mystery",
      "psychological",
      "romance_main",
      "satire",
      "sci_fi",
      "one_shot",
      "thriller",
      "tragedy"
    ]
  },
  {
    "type": "select",
    "id": "types",
    "title": "Type of Story",
    "options": ["ALL", "Original", "Fan Fiction"],
    "ids": ["ALL", "original", "fanfiction"]
  },
  {
    "type": "multi-select",
    "id": "status",
    "title": "Status",
    "canExclude": false,
    "options": [
      "All",
      "Completed",
      "Dropped",
      "Ongoing",
      "Hiatus",
      "Inactive",
      "Stub"
    ],
    "ids": [
      "ALL",
      "COMPLETED",
      "DROPPED",
      "ONGOING",
      "HIATUS",
      "INACTIVE",
      "STUB"
    ]
  },
  {
    "type": "multi-select",
    "id": "content_warnings",
    "title": "Content Warnings",
    "canExclude": true,
    "options": [
      "AI-Assisted Content",
      "AI-Generated Content",
      "Graphic Violence",
      "Profanity",
      "Sensitive Content",
      "Sexual Content"
    ],
    "ids": [
      "ai_assisted",
      "ai_generated",
      "graphic_violence",
      "profanity",
      "sensitive",
      "sexuality"
    ]
  },
  {
    "type": "multi-select",
    "id": "tags",
    "title": "Tags",
    "canExclude": true,
    "options": [
      "Anti-Hero Lead",
      "Artificial Intelligence",
      "Cyberpunk",
      "Dungeon",
      "Dystopia",
      "Female Lead",
      "First Contact",
      "GameLit",
      "Gender Bender",
      "Genetically Engineered",
      "Grimdark",
      "Hard Sci-Fi",
      "Harem",
      "High Fantasy",
      "LitRPG",
      "Loop",
      "Low Fantasy",
      "Magic",
      "Male Lead",
      "Martial Arts",
      "Multiple Lead Characters",
      "Mythos",
      "Non-Human Lead",
      "Portal Fantasy / Isekai",
      "Post Apocalyptic",
      "Progression",
      "Reader Interactive",
      "Reincarnation",
      "Ruling Class",
      "School Life",
      "Secret Identity",
      "Slice of Life",
      "Soft Sci-Fi",
      "Space Opera",
      "Sports",
      "Steampunk",
      "Strategy",
      "Strong Lead",
      "Super Heroes",
      "Supernatural",
      "Technologically Engineered",
      "Time Travel",
      "Urban Fantasy",
      "Villainous Lead",
      "Virtual Reality",
      "War and Military",
      "Wuxia",
      "Xianxia"
    ],
    "ids": [
      "ANTI_HERO_LEAD",
      "ARTIFICIAL_INTELLIGENCE",
      "CYBERPUNK",
      "DUNGEON",
      "DYSTOPIA",
      "FEMALE_LEAD",
      "FIRST_CONTACT",
      "GAMELIT",
      "GENDER_BENDER",
      "GENETICALLY_ENGINEERED",
      "GRIMDARK",
      "HARD_SCI_FI",
      "HAREM",
      "HIGH_FANTASY",
      "LITRPG",
      "LOOP",
      "LOW_FANTASY",
      "MAGIC",
      "MALE_LEAD",
      "MARTIAL_ARTS",
      "MULTIPLE_LEAD_CHARACTERS",
      "MYTHOS",
      "NON_HUMAN_LEAD",
      "SUMMONED_HERO",
      "POST_APOCALYPTIC",
      "PROGRESSION",
      "READER_INTERACTIVE",
      "REINCARNATION",
      "RULING_CLASS",
      "SCHOOL_LIFE",
      "SECRET_IDENTITY",
      "SLICE_OF_LIFE",
      "SOFT_SCI_FI",
      "SPACE_OPERA",
      "SPORTS",
      "STEAMPUNK",
      "STRATEGY",
      "STRONG_LEAD",
      "SUPER_HEROES",
      "SUPERNATURAL",
      "TECHNOLOGICALLY_ENGINEERED",
      "TIME_TRAVEL",
      "URBAN_FANTASY",
      "VILLAINOUS_LEAD",
      "VIRTUAL_REALITY",
      "WAR_AND_MILITARY",
      "WUXIA",
      "XIANXIA"
    ]
  }
]
